{"content": {"suites": {"0": {"status": {"total_pass": 7, "total_skip": 4, "total_xpass": 0, "total_xfail": 0, "total_rerun": 0, "total_fail": 0, "total_error": 0}, "tests": {"0": {"status": "PASS", "message": "", "test_name": "test_valid_student_login[firefox]", "rerun": "0"}, "1": {"status": "PASS", "message": "", "test_name": "test_invalid_student_password[firefox]", "rerun": "0"}, "2": {"status": "PASS", "message": "", "test_name": "test_invalid_student_username[firefox]", "rerun": "0"}, "3": {"status": "PASS", "message": "", "test_name": "test_blank_student_username[firefox]", "rerun": "0"}, "4": {"status": "PASS", "message": "", "test_name": "test_blank_student_password[firefox]", "rerun": "0"}, "5": {"status": "PASS", "message": "", "test_name": "test_blank_student_login[firefox]", "rerun": "0"}, "6": {"status": "PASS", "message": "", "test_name": "test_valid_teaher_login[firefox]", "rerun": "0"}, "7": {"status": "SKIP", "message": "('c:\\\\QA\\\\Dev\\\\projects\\\\fastapi-Vue3\\\\main\\\\Vue3\\\\Tests\\\\test_login.py', 97, 'Skipped: unconditional skip')\n", "test_name": "test_invalid_teacher_password[firefox]", "rerun": "0"}, "8": {"status": "SKIP", "message": "('c:\\\\QA\\\\Dev\\\\projects\\\\fastapi-Vue3\\\\main\\\\Vue3\\\\Tests\\\\test_login.py', 112, 'Skipped: unconditional skip')\n", "test_name": "test_invalid_teacher_username[firefox]", "rerun": "0"}, "9": {"status": "SKIP", "message": "('c:\\\\QA\\\\Dev\\\\projects\\\\fastapi-Vue3\\\\main\\\\Vue3\\\\Tests\\\\test_login.py', 127, 'Skipped: unconditional skip')\n", "test_name": "test_blank_teacher_username[firefox]", "rerun": "0"}, "10": {"status": "SKIP", "message": "('c:\\\\QA\\\\Dev\\\\projects\\\\fastapi-Vue3\\\\main\\\\Vue3\\\\Tests\\\\test_login.py', 143, 'Skipped: unconditional skip')\n", "test_name": "test_blank_teacher_password[firefox]", "rerun": "0"}}, "suite_name": "Tests/test_login.py"}}}, "date": "March 25, 2022", "start_time": 1648270359.9065967, "total_suite": 1, "status": "PASS", "status_list": {"pass": "7", "fail": "0", "skip": "4", "error": "0", "xpass": "0", "xfail": "0", "rerun": "0"}, "total_tests": "11"}